larrydata/__init__.py
larrydata/mturk.py
larrydata/s3.py
larrydata/sagemaker.py
larrydata/sqs.py
larrydata/sts.py
larrydata/utils.py
larrydata/mturk/__init__.py
larrydata/mturk/consolidate.py
larrydata/sagemaker/__init__.py
larrydata/sagemaker/labeling.py
larrydata/utils/__init__.py
larrydata/utils/image.py
test/__init__.py
test/s3.py
test/sagemaker_labeling.py
larrydata-0.2.20.dist-info/LICENSE
larrydata-0.2.20.dist-info/METADATA
larrydata-0.2.20.dist-info/WHEEL
larrydata-0.2.20.dist-info/top_level.txt
larrydata-0.2.20.dist-info/RECORD
