Metadata-Version: 2.1
Name: larrydata
Version: 0.2.20
Summary: Library of helper modules for common data tasks using AWS resources such as S3, SQS, MTurk and others
Home-page: https://github.com/dschultz0/larrydata
Author: Dave Schultz
Author-email: djschult@gmail.com
License: UNKNOWN
Keywords: larry data aws boto3 mturk s3
Platform: UNKNOWN
Classifier: Programming Language :: Python :: 3
Classifier: License :: OSI Approved :: MIT License
Classifier: Operating System :: OS Independent
